rure/__init__.py
rure/_native.py
rure/_native__ffi.py
rure/_native__lib.so
rure/decorators.py
rure/exceptions.py
rure/lib.py
rure/regex.py
rure/tests/__init__.py
rure/tests/test_matchobject.py
rure/tests/test_regexobject.py
rure/tests/test_rure.py
rure/tests/test_rureset.py
kodiak_rure-0.2.3.dist-info/METADATA
kodiak_rure-0.2.3.dist-info/WHEEL
kodiak_rure-0.2.3.dist-info/top_level.txt
kodiak_rure-0.2.3.dist-info/RECORD
